INTCF/__init__.py
intcf-0.1.0.dist-info/METADATA
intcf-0.1.0.dist-info/WHEEL
intcf-0.1.0.dist-info/top_level.txt
intcf-0.1.0.dist-info/RECORD
