Metadata-Version: 2.4
Name: INTCF
Version: 0.1.0
Summary: A Python module that will create the file provided if it doesn'	 exist. 
Author: cocoa
Classifier: Programming Language :: Python :: 3
Classifier: Operating System :: OS Independent
Requires-Python: >=3.7
Dynamic: author
Dynamic: classifier
Dynamic: description
Dynamic: description-content-type
Dynamic: requires-python
Dynamic: summary
